dmodelspy/__init__.py
dmodelspy/mogi.py
dmodelspy/sill.py
dmodelspy/sphere2D.py
dmodelspy/sphere3D.py
dmodelspy/spheroid.py
dmodelspy/version.py
dmodelspy-0.2.dist-info/METADATA
dmodelspy-0.2.dist-info/WHEEL
dmodelspy-0.2.dist-info/top_level.txt
dmodelspy-0.2.dist-info/RECORD
