Metadata-Version: 2.1
Name: dmodelspy
Version: 0.2
Summary: Python port of dMODELS
Home-page: https://github.com/WayneCrawford/dmodelspy
Author: Wayne Crawford
Author-email: crawford@ipgp.fr
License: UNKNOWN
Keywords: geodesy
Platform: UNKNOWN
Classifier: Development Status :: 4 - Beta
Classifier: Environment :: Console
Classifier: Intended Audience :: Science/Research
Classifier: Intended Audience :: Developers
Classifier: License :: OSI Approved :: GNU General Public License v3 (GPLv3)
Classifier: Natural Language :: English
Classifier: Operating System :: OS Independent
Classifier: Programming Language :: Python :: 3
Classifier: Programming Language :: Python :: 3.7
Classifier: Topic :: Scientific/Engineering
Classifier: Topic :: Scientific/Engineering :: Physics
Requires-Python: >=3.7
Requires-Dist: numpy (>=1.1)
Requires-Dist: scipy (>=1.4)
Requires-Dist: matplotlib (>=3.0)
Requires-Dist: pandas (>=1.1)
